Metadata-Version: 2.1
Name: autora-experimentalist-inequality
Version: 2.2.0
Summary: AutoRA Inequality Experimentalist
Author-email: "Chad C. Williams" <cwilliams.uca@gmail.com>, Younes Strittmatter <younes_strittmatter@brown.com>
License: MIT License
Project-URL: homepage, http://www.empiricalresearch.ai
Project-URL: repository, https://github.com/AutoResearch/autora-experimentalist-inequality
Project-URL: documentation, https://autoresearch.github.io/autora/
Requires-Python: <4,>=3.8
License-File: LICENSE
Requires-Dist: autora-core >=3.1.0
Provides-Extra: dev
Requires-Dist: autora-core[dev] ; extra == 'dev'
